grafap/__init__.py
grafap/_auth.py
grafap/_helpers.py
grafap/lists.py
grafap/onenote.py
grafap/sites.py
grafap/termstore.py
grafap/users.py
grafap-0.1.13.dist-info/WHEEL
grafap-0.1.13.dist-info/METADATA
grafap-0.1.13.dist-info/RECORD
