Metadata-Version: 2.3
Name: grafap
Version: 0.1.13
Summary: Python package that acts as a wrapper for the Microsoft Graph API.
Author: Jordan Maynor
Author-email: Jordan Maynor <jmaynor@pepsimidamerica.com>
License: This is free and unencumbered software released into the public domain.
Classifier: Programming Language :: Python :: 3
Classifier: License :: OSI Approved :: The Unlicense (Unlicense)
Classifier: Operating System :: OS Independent
Requires-Dist: cryptography>=45.0.5
Requires-Dist: pyjwt>=2.10.1
Requires-Dist: pyopenssl>=25.1.0
Requires-Dist: requests>=2.32.4
Requires-Dist: tenacity>=9.1.2
Requires-Python: >=3.11
Project-URL: Homepage, https://github.com/pepsimidamerica/grafap
